django_suit_dashboard-2.0.6.dist-info/DESCRIPTION.rst
django_suit_dashboard-2.0.6.dist-info/METADATA
django_suit_dashboard-2.0.6.dist-info/RECORD
django_suit_dashboard-2.0.6.dist-info/WHEEL
django_suit_dashboard-2.0.6.dist-info/metadata.json
django_suit_dashboard-2.0.6.dist-info/top_level.txt
suit_dashboard/__init__.py
suit_dashboard/apps.py
suit_dashboard/layout.py
suit_dashboard/models.py
suit_dashboard/urls.py
suit_dashboard/views.py
suit_dashboard/widgets.py
suit_dashboard/static/suit_dashboard/base.css
suit_dashboard/templates/suit_dashboard/base.html
suit_dashboard/templates/suit_dashboard/box.html
suit_dashboard/templates/suit_dashboard/element.html
suit_dashboard/templates/suit_dashboard/row.html
