Metadata-Version: 2.0
Name: django-suit-dashboard
Version: 2.0.6
Summary: Create a dashboard within Django admin interface
Home-page: https://github.com/Pawamoy/django-suit-dashboard
Author: Timothee Mazzucotelli
Author-email: timothee.mazzucotelli@gmail.com
License: ISC
Keywords: django-suit-dashboard
Platform: UNKNOWN
Classifier: Development Status :: 4 - Beta
Classifier: Intended Audience :: Developers
Classifier: License :: OSI Approved :: ISC License (ISCL)
Classifier: Operating System :: Unix
Classifier: Framework :: Django
Classifier: Programming Language :: Python
Classifier: Programming Language :: Python :: 2.7
Classifier: Programming Language :: Python :: 3
Classifier: Programming Language :: Python :: 3.4
Classifier: Programming Language :: Python :: 3.5
Classifier: Programming Language :: Python :: 3.6
Classifier: Programming Language :: Python :: Implementation :: PyPy
Classifier: Topic :: Utilities
Requires-Dist: django-app-settings
Requires-Dist: django-braces
